up_enhsp/__init__.py
up_enhsp/enhsp_planner.py
up_enhsp/ENHSP/enhsp.jar
up_enhsp/ENHSP/libs/JPddl_.jar
up_enhsp/ENHSP/libs/antlr-3.4-complete.jar
up_enhsp/ENHSP/libs/commons-cli-1.4.jar
up_enhsp/ENHSP/libs/commons-collections4-4.3.jar
up_enhsp/ENHSP/libs/commons-lang3-3.8.1.jar
up_enhsp/ENHSP/libs/fastutil-8.3.1.jar
up_enhsp/ENHSP/libs/guava-26.0-jre.jar
up_enhsp/ENHSP/libs/hamcrest-core-1.3.jar
up_enhsp/ENHSP/libs/hppc-0.8.0-SNAPSHOT.jar
up_enhsp/ENHSP/libs/ia_math.jar
up_enhsp/ENHSP/libs/jgrapht-core-1.3.0.jar
up_enhsp/ENHSP/libs/json-simple-1.1.1.jar
up_enhsp-0.1.0.dist-info/licenses/LICENSE
up_enhsp-0.1.0.dist-info/METADATA
up_enhsp-0.1.0.dist-info/WHEEL
up_enhsp-0.1.0.dist-info/top_level.txt
up_enhsp-0.1.0.dist-info/RECORD
