Metadata-Version: 2.4
Name: up_enhsp
Version: 0.1.0
Summary: up_enhsp
Author: UNIBS Team
Author-email: enrico.scala@unibs.it
License: APACHE
License-File: LICENSE
Dynamic: author
Dynamic: author-email
Dynamic: license
Dynamic: license-file
Dynamic: summary
